odoo10_addon_l10n_fi_payment_terms-10.0.1.1.1-py2.7-nspkg.pth
odoo/addons/l10n_fi_payment_terms/README.rst
odoo/addons/l10n_fi_payment_terms/__init__.py
odoo/addons/l10n_fi_payment_terms/__manifest__.py
odoo/addons/l10n_fi_payment_terms/data/payment_terms_finnish.xml
odoo/addons/l10n_fi_payment_terms/i18n/fi.po
odoo/addons/l10n_fi_payment_terms/models/__init__.py
odoo/addons/l10n_fi_payment_terms/models/payment_term.py
odoo/addons/l10n_fi_payment_terms/static/description/icon.png
odoo10_addon_l10n_fi_payment_terms-10.0.1.1.1.dist-info/DESCRIPTION.rst
odoo10_addon_l10n_fi_payment_terms-10.0.1.1.1.dist-info/METADATA
odoo10_addon_l10n_fi_payment_terms-10.0.1.1.1.dist-info/RECORD
odoo10_addon_l10n_fi_payment_terms-10.0.1.1.1.dist-info/WHEEL
odoo10_addon_l10n_fi_payment_terms-10.0.1.1.1.dist-info/metadata.json
odoo10_addon_l10n_fi_payment_terms-10.0.1.1.1.dist-info/namespace_packages.txt
odoo10_addon_l10n_fi_payment_terms-10.0.1.1.1.dist-info/top_level.txt
