Metadata-Version: 2.0
Name: odoo10-addon-l10n-fi-payment-terms
Version: 10.0.1.1.1
Summary: Common Finnish invoice payment terms
Home-page: https://odoo-community.org/
Author: Oy Tawasta Technologies Ltd., Odoo Community Association (OCA)
Author-email: support@odoo-community.org
License: AGPL-3
Platform: UNKNOWN
Classifier: Programming Language :: Python
Classifier: Framework :: Odoo
Classifier: License :: OSI Approved :: GNU Affero General Public License v3
Requires-Python: ~=2.7
Requires-Dist: odoo (<10.1dev,>=10.0)
